{"cameraMode":{"drawMode":0,"name":"Shaded","section":"Shading Mode"},"sceneLighting":true,"audioPlay":false,"sceneViewState":{"showFog":true,"showMaterialUpdate":false,"showSkybox":true,"showFlares":true,"showImageEffects":true,"showParticleSystems":true,"showVisualEffectGraphs":true,"m_FxEnabled":false},"in2DMode":false,"pivot":{"x":0.7361328601837158,"y":2.841078519821167,"z":-0.3599989414215088},"rotation":{"x":0.1629018485546112,"y":0.8060672879219055,"z":-0.25887054204940798,"w":0.5068457126617432},"size":1.9909517765045167,"orthographic":false}